yaso_paste/__init__.py
yaso_paste/api.py
yaso_paste-3.0.0.dist-info/METADATA
yaso_paste-3.0.0.dist-info/WHEEL
yaso_paste-3.0.0.dist-info/top_level.txt
yaso_paste-3.0.0.dist-info/RECORD
