Metadata-Version: 2.4
Name: yaso-paste
Version: 3.0.0
Summary: Simple async Python library to paste text or files to yaso.su
Home-page: https://github.com/Arctixinc/yaso_paste
Author: Arctix
Author-email: Arctix <inc.arctix@gmail.com>
License: MIT
Classifier: Programming Language :: Python :: 3
Classifier: License :: OSI Approved :: MIT License
Classifier: Operating System :: OS Independent
Requires-Python: >=3.8
Requires-Dist: aiohttp>=3.8
Dynamic: author
Dynamic: home-page
Dynamic: requires-python
